scquill/__init__.py
scquill/approximation.py
scquill/compressor.py
scquill/io/__init__.py
scquill/io/read.py
scquill/io/write.py
scquill/pl/__init__.py
scquill/pl/dotplot.py
scquill/pl/embedding.py
scquill/pl/neighborhood_composition.py
scquill/pl/neighborhoodplot.py
scquill/utils/__init__.py
scquill/utils/coarse_grain.py
scquill/utils/compress/__init__.py
scquill/utils/compress/biological.py
scquill/utils/compress/neighborhood.py
scquill/utils/concatenate.py
scquill/utils/config.py
scquill/utils/heuristics.py
scquill/utils/preprocess.py
scquill/utils/types.py
scquill-0.3.2.dist-info/LICENSE
scquill-0.3.2.dist-info/METADATA
scquill-0.3.2.dist-info/WHEEL
scquill-0.3.2.dist-info/RECORD
