Metadata-Version: 2.1
Name: scquill
Version: 0.3.2
Summary: Approximate any single cell data set, saving >99% of memory and runtime.
License: MIT
Author: Fabio Zanini
Author-email: fabio.zanini@unsw.edu.au
Requires-Python: >=3.11,<3.13
Classifier: License :: OSI Approved :: MIT License
Classifier: Programming Language :: Python :: 3
Classifier: Programming Language :: Python :: 3.11
Classifier: Programming Language :: Python :: 3.12
Requires-Dist: h5py (>=3.10.0,<4.0.0)
Requires-Dist: hdf5plugin (>=4.2.0,<5.0.0)
Requires-Dist: pyyaml (>=6.0.1,<7.0.0)
Requires-Dist: scanpy (>=1.9.6,<2.0.0)
